{"fcd72fa5e7":{"name":"675","key":"675","osrs_total":110160,"rs3_total":0,"combined_total":110160,"leagues":{"TL":[630,61775],"TBL":[27550,null],"TBLR":[21880,112976],"REL":[60100,12718]}},"08fa232dcd":{"name":"678m","key":"678m","osrs_total":1260,"rs3_total":0,"combined_total":1260,"leagues":{"TBL":[1260,null]}},"a033a79002":{"name":"67dingohide","key":"67dingohide","osrs_total":14050,"rs3_total":0,"combined_total":14050,"leagues":{"TBL":[14050,null]}},"c3f1d2d420":{"name":"6714","key":"6714","osrs_total":6345,"rs3_total":0,"combined_total":6345,"leagues":{"SRL":[6345,68810]}},"eb6bfd7992":{"name":"67 Fury 1128","key":"67 fury 1128","osrs_total":8205,"rs3_total":0,"combined_total":8205,"leagues":{"SRL":[3405,88759],"TBLR":[3470,254598],"REL":[1330,351301]}},"2dbb579958":{"name":"6788233055","key":"6788233055","osrs_total":2210,"rs3_total":0,"combined_total":2210,"leagues":{"SRL":[2210,99601]}},"887cb14933":{"name":"67 Pixels","key":"67 pixels","osrs_total":1415,"rs3_total":0,"combined_total":1415,"leagues":{"SRL":[1415,114590]}},"6cf04485aa":{"name":"67 Death2all","key":"67 death2all","osrs_total":87645,"rs3_total":0,"combined_total":87645,"leagues":{"SRL":[635,137640],"TBLR":[56000,12732],"REL":[31010,79570]}},"f86d17c472":{"name":"67 Gold 1889","key":"67 gold 1889","osrs_total":135,"rs3_total":0,"combined_total":135,"leagues":{"SRL":[135,173992]}},"071ae3f61f":{"name":"674k","key":"674k","osrs_total":39550,"rs3_total":0,"combined_total":39550,"leagues":{"TBLR":[39550,27866]}},"95149e08db":{"name":"6 7 8 9","key":"6 7 8 9","osrs_total":44800,"rs3_total":0,"combined_total":44800,"leagues":{"TBLR":[17120,141758],"REL":[27680,109019]}},"98b2b841ed":{"name":"67lL","key":"67ll","osrs_total":16340,"rs3_total":0,"combined_total":16340,"leagues":{"TBLR":[16340,148105]}},"d2c25f6839":{"name":"67kc dfs btw","key":"67kc dfs btw","osrs_total":10390,"rs3_total":0,"combined_total":10390,"leagues":{"TBLR":[10390,185558]}},"550ba1248d":{"name":"67 Dinky 220","key":"67 dinky 220","osrs_total":7940,"rs3_total":0,"combined_total":7940,"leagues":{"TBLR":[7940,206193]}},"f3d860497f":{"name":"67deadlyroc","key":"67deadlyroc","osrs_total":5310,"rs3_total":0,"combined_total":5310,"leagues":{"TBLR":[2960,262545],"REL":[2350,331161]}},"e7e5a2302f":{"name":"67hellion343","key":"67hellion343","osrs_total":2420,"rs3_total":0,"combined_total":2420,"leagues":{"TBLR":[2420,272732]}},"710b28ec9a":{"name":"67short2","key":"67short2","osrs_total":9200,"rs3_total":0,"combined_total":9200,"leagues":{"TBLR":[2140,278889],"REL":[7060,280999]}},"8e1c934390":{"name":"67xvbz","key":"67xvbz","osrs_total":1740,"rs3_total":0,"combined_total":1740,"leagues":{"TBLR":[1740,286442]}},"e1fe49d988":{"name":"67 N00b Ice","key":"67 n00b ice","osrs_total":910,"rs3_total":0,"combined_total":910,"leagues":{"TBLR":[910,309143]}},"d559910190":{"name":"67mustang6","key":"67mustang6","osrs_total":680,"rs3_total":0,"combined_total":680,"leagues":{"TBLR":[680,318192]}},"325faed81f":{"name":"67rs","key":"67rs","osrs_total":61580,"rs3_total":0,"combined_total":61580,"leagues":{"REL":[61580,4929]}},"b5d6c477ea":{"name":"67six7","key":"67six7","osrs_total":52960,"rs3_total":0,"combined_total":52960,"leagues":{"REL":[52960,25427]}},"90d8e7fc59":{"name":"67 zyn","key":"67 zyn","osrs_total":45160,"rs3_total":0,"combined_total":45160,"leagues":{"REL":[45160,36348]}},"c6b0577315":{"name":"6 7 ern","key":"6 7 ern","osrs_total":41170,"rs3_total":440,"combined_total":41610,"leagues":{"REL":[41170,44822],"CATA":[440,110223]}},"a2bae545e6":{"name":"67k Files","key":"67k files","osrs_total":40780,"rs3_total":0,"combined_total":40780,"leagues":{"REL":[40780,45436]}},"82a96f0cdf":{"name":"67 Six Seven","key":"67 six seven","osrs_total":34160,"rs3_total":0,"combined_total":34160,"leagues":{"REL":[34160,62850]}},"c9e3fd7a64":{"name":"679jrjviqu","key":"679jrjviqu","osrs_total":29770,"rs3_total":0,"combined_total":29770,"leagues":{"REL":[29770,92506]}},"f390d9de32":{"name":"67 69 67 69","key":"67 69 67 69","osrs_total":29690,"rs3_total":0,"combined_total":29690,"leagues":{"REL":[29690,92919]}},"83c6fde429":{"name":"67676767","key":"67676767","osrs_total":27950,"rs3_total":0,"combined_total":27950,"leagues":{"REL":[27950,106494]}},"e429442fe3":{"name":"67drivecook","key":"67drivecook","osrs_total":25900,"rs3_total":0,"combined_total":25900,"leagues":{"REL":[25900,130703]}},"143f0a30a7":{"name":"67ioc","key":"67ioc","osrs_total":23610,"rs3_total":0,"combined_total":23610,"leagues":{"REL":[23610,148771]}},"4c8c9f7f9d":{"name":"67james555","key":"67james555","osrs_total":20470,"rs3_total":0,"combined_total":20470,"leagues":{"REL":[20470,168205]}},"0b8f748446":{"name":"67 Shab Ybab","key":"67 shab ybab","osrs_total":17830,"rs3_total":0,"combined_total":17830,"leagues":{"REL":[17830,192133]}},"ca9f3696bb":{"name":"67 Fair 1229","key":"67 fair 1229","osrs_total":16640,"rs3_total":0,"combined_total":16640,"leagues":{"REL":[16640,203203]}},"5c78472f2a":{"name":"67dark2730","key":"67dark2730","osrs_total":10740,"rs3_total":0,"combined_total":10740,"leagues":{"REL":[10740,242844]}},"46ea89dc96":{"name":"67VAG","key":"67vag","osrs_total":10020,"rs3_total":0,"combined_total":10020,"leagues":{"REL":[10020,250656]}},"1325b605ca":{"name":"67LCummins","key":"67lcummins","osrs_total":9690,"rs3_total":0,"combined_total":9690,"leagues":{"REL":[9690,254320]}},"bc7cd72bb1":{"name":"67e","key":"67e","osrs_total":7700,"rs3_total":0,"combined_total":7700,"leagues":{"REL":[7700,275722]}},"e6ae7ee778":{"name":"67 Ghrim 826","key":"67 ghrim 826","osrs_total":7560,"rs3_total":0,"combined_total":7560,"leagues":{"REL":[7560,276714]}},"75aebbfd6f":{"name":"6 7 Wolf","key":"6 7 wolf","osrs_total":5570,"rs3_total":0,"combined_total":5570,"leagues":{"REL":[5570,296686]}},"3448601f11":{"name":"67inyomama","key":"67inyomama","osrs_total":2180,"rs3_total":2040,"combined_total":4220,"leagues":{"REL":[2180,333808],"CATA":[2040,84218]}},"c0c79f3bff":{"name":"67frozen2042","key":"67frozen2042","osrs_total":2100,"rs3_total":0,"combined_total":2100,"leagues":{"REL":[2100,335396]}},"8adcf0f6bb":{"name":"67fiery2421","key":"67fiery2421","osrs_total":1130,"rs3_total":0,"combined_total":1130,"leagues":{"REL":[1130,356289]}},"0b1f67e5d9":{"name":"67dragon2555","key":"67dragon2555","osrs_total":1080,"rs3_total":0,"combined_total":1080,"leagues":{"REL":[1080,357849]}},"6867240ead":{"name":"67impala93","key":"67impala93","osrs_total":360,"rs3_total":0,"combined_total":360,"leagues":{"REL":[360,385899]}},"132b0e1623":{"name":"67 Kaan 1523","key":"67 kaan 1523","osrs_total":0,"rs3_total":13380,"combined_total":13380,"leagues":{"CATA":[13380,45063]}},"7d695548f8":{"name":"6789","key":"6789","osrs_total":0,"rs3_total":2220,"combined_total":2220,"leagues":{"CATA":[2220,81718]}},"7cc95669db":{"name":"67 Death 675","key":"67 death 675","osrs_total":0,"rs3_total":2060,"combined_total":2060,"leagues":{"CATA":[2060,83938]}}}