{"ea20c9b60e":{"name":"9point8","key":"9point8","osrs_total":43985,"rs3_total":15590,"combined_total":59575,"leagues":{"TL":[4240,24930],"SRL":[12755,41851],"REL":[26990,116645],"CATA":[15590,39985]}},"856725fc39":{"name":"9POW","key":"9pow","osrs_total":59080,"rs3_total":0,"combined_total":59080,"leagues":{"TBL":[300,null],"SRL":[28870,11234],"TBLR":[2420,272884],"REL":[27490,111052]}},"d2e8fce16b":{"name":"9pyramidlaps","key":"9pyramidlaps","osrs_total":44440,"rs3_total":0,"combined_total":44440,"leagues":{"TBLR":[25700,88568],"REL":[18740,183861]}},"e4ba1d3207":{"name":"9 P 9","key":"9 p 9","osrs_total":21410,"rs3_total":0,"combined_total":21410,"leagues":{"TBLR":[18030,134893],"REL":[3380,317374]}},"20c2d523fe":{"name":"9PointG","key":"9pointg","osrs_total":2080,"rs3_total":0,"combined_total":2080,"leagues":{"TBLR":[2080,280264]}},"f3590d8743":{"name":"9 Pnizz","key":"9 pnizz","osrs_total":9490,"rs3_total":270,"combined_total":9760,"leagues":{"REL":[9490,256521],"CATA":[270,115434]}},"59339fb7a0":{"name":"9 past Marky","key":"9 past marky","osrs_total":6660,"rs3_total":0,"combined_total":6660,"leagues":{"REL":[6660,285033]}},"0212b267e0":{"name":"9 Percent","key":"9 percent","osrs_total":360,"rs3_total":0,"combined_total":360,"leagues":{"REL":[360,385453]}},"ce85cd2694":{"name":"9pH","key":"9ph","osrs_total":0,"rs3_total":6390,"combined_total":6390,"leagues":{"CATA":[6390,61516]}}}