{"ec800c5a2c":{"name":"lZephyrl","key":"lzephyrl","osrs_total":65380,"rs3_total":0,"combined_total":65380,"leagues":{"TL":[15110,2118],"TBL":[50270,4065]}},"e7af134457":{"name":"lZypeR","key":"lzyper","osrs_total":8570,"rs3_total":0,"combined_total":8570,"leagues":{"TL":[8570,8215]}},"5bce6ff6ec":{"name":"l Zander l","key":"l zander l","osrs_total":6030,"rs3_total":0,"combined_total":6030,"leagues":{"TL":[6030,17756]}},"1643f9b147":{"name":"LzrBeam","key":"lzrbeam","osrs_total":51040,"rs3_total":0,"combined_total":51040,"leagues":{"TL":[4290,24736],"TBLR":[4410,243927],"REL":[42340,43250]}},"560f07b4d3":{"name":"lzly","key":"lzly","osrs_total":10,"rs3_total":0,"combined_total":10,"leagues":{"TL":[10,108969]}},"a8d017e3b8":{"name":"LZB Monkey","key":"lzb monkey","osrs_total":10269,"rs3_total":0,"combined_total":10269,"leagues":{"TBL":[-1,null],"SRL":[2270,98825],"REL":[8000,274205]}},"0d00e5e5e2":{"name":"lzuna","key":"lzuna","osrs_total":0,"rs3_total":0,"combined_total":0,"leagues":{"TBL":[0,null]}},"6864af8cea":{"name":"lzzie","key":"lzzie","osrs_total":31295,"rs3_total":0,"combined_total":31295,"leagues":{"SRL":[31295,9531]}},"16a4889737":{"name":"LZS","key":"lzs","osrs_total":33835,"rs3_total":0,"combined_total":33835,"leagues":{"SRL":[8065,61900],"REL":[25770,132479]}},"587e89a197":{"name":"LZRD iiitz","key":"lzrd iiitz","osrs_total":3595,"rs3_total":0,"combined_total":3595,"leagues":{"SRL":[3595,86807]}},"d91de64c06":{"name":"lzdlt","key":"lzdlt","osrs_total":1850,"rs3_total":0,"combined_total":1850,"leagues":{"SRL":[1850,105354]}},"7ef7a06827":{"name":"lzrop","key":"lzrop","osrs_total":25605,"rs3_total":0,"combined_total":25605,"leagues":{"SRL":[1245,117956],"TBLR":[7650,208812],"REL":[16710,202453]}},"9168fa143b":{"name":"l zerk","key":"l zerk","osrs_total":1100,"rs3_total":0,"combined_total":1100,"leagues":{"SRL":[1100,121474]}},"0a0a7cda17":{"name":"lzyfck","key":"lzyfck","osrs_total":960,"rs3_total":0,"combined_total":960,"leagues":{"SRL":[560,141517],"REL":[400,383165]}},"a31c3d029e":{"name":"LzC4","key":"lzc4","osrs_total":21875,"rs3_total":28400,"combined_total":50275,"leagues":{"SRL":[165,169231],"TBLR":[5540,228090],"REL":[16170,207440],"CATA":[28400,19190]}},"9ae478b0fd":{"name":"Lzh1703","key":"lzh1703","osrs_total":90900,"rs3_total":0,"combined_total":90900,"leagues":{"TBLR":[42780,20598],"REL":[48120,29526]}},"34b87d4285":{"name":"LZ Xolder","key":"lz xolder","osrs_total":33990,"rs3_total":0,"combined_total":33990,"leagues":{"TBLR":[33990,39395]}},"ce4db9929d":{"name":"LzyConductor","key":"lzyconductor","osrs_total":42050,"rs3_total":0,"combined_total":42050,"leagues":{"TBLR":[33180,41934],"REL":[8870,263596]}},"078dedf1c2":{"name":"LZ JW","key":"lz jw","osrs_total":27630,"rs3_total":0,"combined_total":27630,"leagues":{"TBLR":[27630,73360]}},"b6448a91bc":{"name":"LZNZ","key":"lznz","osrs_total":26650,"rs3_total":0,"combined_total":26650,"leagues":{"TBLR":[26650,80177]}},"4df851f479":{"name":"LzyMilennial","key":"lzymilennial","osrs_total":34470,"rs3_total":0,"combined_total":34470,"leagues":{"TBLR":[18080,134411],"REL":[16390,205535]}},"5e6608a576":{"name":"lZeeX","key":"lzeex","osrs_total":42950,"rs3_total":0,"combined_total":42950,"leagues":{"TBLR":[15930,151569],"REL":[27020,116268]}},"7ee8cf77db":{"name":"LzyI","key":"lzyi","osrs_total":15480,"rs3_total":0,"combined_total":15480,"leagues":{"TBLR":[15480,155257]}},"b2200de973":{"name":"lzc2","key":"lzc2","osrs_total":15080,"rs3_total":0,"combined_total":15080,"leagues":{"TBLR":[15080,158567]}},"23fd27a921":{"name":"lZamorakl","key":"lzamorakl","osrs_total":43850,"rs3_total":29790,"combined_total":73640,"leagues":{"TBLR":[14570,159989],"REL":[29280,95476],"CATA":[29790,18016]}},"27babeda74":{"name":"lzzl","key":"lzzl","osrs_total":36940,"rs3_total":0,"combined_total":36940,"leagues":{"TBLR":[9760,191115],"REL":[27180,114415]}},"dc4779b640":{"name":"LzrdBlzrd2","key":"lzrdblzrd2","osrs_total":6650,"rs3_total":0,"combined_total":6650,"leagues":{"TBLR":[6650,215330]}},"a7a68a3108":{"name":"lzsd","key":"lzsd","osrs_total":3880,"rs3_total":0,"combined_total":3880,"leagues":{"TBLR":[3880,250097]}},"38c22dfd58":{"name":"Lzy H","key":"lzy h","osrs_total":2280,"rs3_total":0,"combined_total":2280,"leagues":{"TBLR":[2280,275890]}},"4a8699a79d":{"name":"LzrdBlzrd1","key":"lzrdblzrd1","osrs_total":2160,"rs3_total":0,"combined_total":2160,"leagues":{"TBLR":[2160,278491]}},"4753ed9b98":{"name":"LzrdSandwich","key":"lzrdsandwich","osrs_total":32160,"rs3_total":0,"combined_total":32160,"leagues":{"TBLR":[1500,292082],"REL":[30660,82211]}},"3c22d1f197":{"name":"Lzcifzr","key":"lzcifzr","osrs_total":660,"rs3_total":0,"combined_total":660,"leagues":{"TBLR":[660,318981]}},"f94639c2e1":{"name":"l ZANZA l","key":"l zanza l","osrs_total":3060,"rs3_total":0,"combined_total":3060,"leagues":{"TBLR":[510,326227],"REL":[2550,328971]}},"e2a050f788":{"name":"l Zekken l","key":"l zekken l","osrs_total":310,"rs3_total":0,"combined_total":310,"leagues":{"TBLR":[310,338137]}},"5bb2a9875a":{"name":"lZiot","key":"lziot","osrs_total":60410,"rs3_total":0,"combined_total":60410,"leagues":{"REL":[60410,8239]}},"85b0b34207":{"name":"lzzys main","key":"lzzys main","osrs_total":38050,"rs3_total":0,"combined_total":38050,"leagues":{"REL":[38050,50767]}},"b28aee1843":{"name":"lzyTrainman","key":"lzytrainman","osrs_total":36940,"rs3_total":0,"combined_total":36940,"leagues":{"REL":[36940,53576]}},"7c28f5a120":{"name":"L ze","key":"l ze","osrs_total":31650,"rs3_total":0,"combined_total":31650,"leagues":{"REL":[31650,75348]}},"440565650a":{"name":"LZWD","key":"lzwd","osrs_total":30170,"rs3_total":0,"combined_total":30170,"leagues":{"REL":[30170,86952]}},"c29ed450c0":{"name":"[#LZCWIIJUI]","key":"[#lzcwiijui]","osrs_total":26260,"rs3_total":0,"combined_total":26260,"leagues":{"REL":[26260,125760]}},"42d1339202":{"name":"l zzy","key":"l zzy","osrs_total":25870,"rs3_total":0,"combined_total":25870,"leagues":{"REL":[25870,131088]}},"61a2203caa":{"name":"lzam","key":"lzam","osrs_total":25070,"rs3_total":0,"combined_total":25070,"leagues":{"REL":[25070,143487]}},"e67d9a3191":{"name":"LZB Wurmple","key":"lzb wurmple","osrs_total":24360,"rs3_total":0,"combined_total":24360,"leagues":{"REL":[24360,146485]}},"53d9b5fb00":{"name":"lzrlkq","key":"lzrlkq","osrs_total":21150,"rs3_total":0,"combined_total":21150,"leagues":{"REL":[21150,162703]}},"f23bef6cd8":{"name":"l Zwellix l","key":"l zwellix l","osrs_total":19010,"rs3_total":0,"combined_total":19010,"leagues":{"REL":[19010,181537]}},"4f36ebe814":{"name":"l-Zoobe-l","key":"l-zoobe-l","osrs_total":10210,"rs3_total":0,"combined_total":10210,"leagues":{"REL":[10210,248335]}},"106367abea":{"name":"lz6","key":"lz6","osrs_total":8330,"rs3_total":0,"combined_total":8330,"leagues":{"REL":[8330,270166]}},"25527692a5":{"name":"lZl-Jr-lZl","key":"lzl-jr-lzl","osrs_total":8170,"rs3_total":0,"combined_total":8170,"leagues":{"REL":[8170,272085]}},"b8c747d728":{"name":"lzakov","key":"lzakov","osrs_total":5910,"rs3_total":0,"combined_total":5910,"leagues":{"REL":[5910,293382]}},"a58b177e78":{"name":"l Zixx l","key":"l zixx l","osrs_total":5290,"rs3_total":0,"combined_total":5290,"leagues":{"REL":[5290,299193]}},"ff122a4ba3":{"name":"LzrdBlzrd","key":"lzrdblzrd","osrs_total":3620,"rs3_total":0,"combined_total":3620,"leagues":{"REL":[3620,314347]}},"5f79d4fec4":{"name":"lzekiel","key":"lzekiel","osrs_total":1330,"rs3_total":0,"combined_total":1330,"leagues":{"REL":[1330,351186]}},"ac2260b0e0":{"name":"lzaar","key":"lzaar","osrs_total":780,"rs3_total":0,"combined_total":780,"leagues":{"REL":[780,366413]}},"b6c7e61ee7":{"name":"l Zenro l","key":"l zenro l","osrs_total":460,"rs3_total":0,"combined_total":460,"leagues":{"REL":[460,378950]}},"d4346ecbaa":{"name":"Lzea","key":"lzea","osrs_total":0,"rs3_total":63500,"combined_total":63500,"leagues":{"CATA":[63500,2440]}},"8aca7dc262":{"name":"lZaros","key":"lzaros","osrs_total":0,"rs3_total":48860,"combined_total":48860,"leagues":{"CATA":[48860,7443]}},"d2b1db819e":{"name":"lZ4C","key":"lz4c","osrs_total":0,"rs3_total":30600,"combined_total":30600,"leagues":{"CATA":[30600,16276]}},"866d6218ff":{"name":"LzHoshi","key":"lzhoshi","osrs_total":0,"rs3_total":22570,"combined_total":22570,"leagues":{"CATA":[22570,30817]}},"77e91d2a1d":{"name":"Lzy","key":"lzy","osrs_total":0,"rs3_total":16020,"combined_total":16020,"leagues":{"CATA":[16020,38995]}},"69c07b3800":{"name":"Lz Dz","key":"lz dz","osrs_total":0,"rs3_total":6490,"combined_total":6490,"leagues":{"CATA":[6490,60990]}}}