{"950be4f71d":{"name":"Z3","key":"z3","osrs_total":20880,"rs3_total":0,"combined_total":20880,"osrs_rank":266707,"rs3_rank":805674,"combined_rank":293924,"leagues":{"TL":[15490,2016,"Rune"],"SRL":[4450,79348,"Steel"],"REL":[940,362179,null]},"perfect_osrs":false,"perfect_rs3":false,"perfect_combined":false},"321bd687f4":{"name":"Z3XY","key":"z3xy","osrs_total":8940,"rs3_total":0,"combined_total":8940,"osrs_rank":402856,"rs3_rank":805731,"combined_rank":439695,"leagues":{"TL":[8940,7695,"Adamant"]},"perfect_osrs":false,"perfect_rs3":false,"perfect_combined":false},"60b80d6d76":{"name":"z33z","key":"z33z","osrs_total":5990,"rs3_total":0,"combined_total":5990,"osrs_rank":453485,"rs3_rank":805680,"combined_rank":496590,"leagues":{"TL":[4160,25211,"Mithril"],"TBLR":[1360,296262,null],"REL":[470,378677,null]},"perfect_osrs":false,"perfect_rs3":false,"perfect_combined":false},"952f88f739":{"name":"Z3U5 JU1C3","key":"z3u5 ju1c3","osrs_total":2650,"rs3_total":0,"combined_total":2650,"osrs_rank":532773,"rs3_rank":805729,"combined_rank":583746,"leagues":{"TL":[2650,36538,"Mithril"]},"perfect_osrs":false,"perfect_rs3":false,"perfect_combined":false},"79689e230c":{"name":"Z3zo3a","key":"z3zo3a","osrs_total":900,"rs3_total":0,"combined_total":900,"osrs_rank":615089,"rs3_rank":805732,"combined_rank":679118,"leagues":{"TL":[900,55489,"Steel"]},"perfect_osrs":false,"perfect_rs3":false,"perfect_combined":false},"05215dff57":{"name":"Z3ntangle","key":"z3ntangle","osrs_total":40830,"rs3_total":0,"combined_total":40830,"osrs_rank":122340,"rs3_rank":805698,"combined_rank":136638,"leagues":{"TL":[230,75965,"Iron"],"TBLR":[22910,110260,"Mithril"],"REL":[17690,193464,"Steel"]},"perfect_osrs":false,"perfect_rs3":false,"perfect_combined":false},"820ef02d0d":{"name":"Z3R0 B4NK","key":"z3r0 b4nk","osrs_total":190,"rs3_total":0,"combined_total":190,"osrs_rank":700904,"rs3_rank":805703,"combined_rank":774781,"leagues":{"TL":[190,78435,"Iron"]},"perfect_osrs":false,"perfect_rs3":false,"perfect_combined":false},"fcb8554587":{"name":"Z3 P","key":"z3 p","osrs_total":0,"rs3_total":0,"combined_total":0,"osrs_rank":740381,"rs3_rank":805676,"combined_rank":815723,"leagues":{"TBL":[0,37923,null]},"perfect_osrs":false,"perfect_rs3":false,"perfect_combined":false},"2c9c8bc602":{"name":"z31guy","key":"z31guy","osrs_total":0,"rs3_total":0,"combined_total":0,"osrs_rank":740382,"rs3_rank":805678,"combined_rank":815724,"leagues":{"TBL":[0,37924,null]},"perfect_osrs":false,"perfect_rs3":false,"perfect_combined":false},"8d825859ac":{"name":"z3nyatta","key":"z3nyatta","osrs_total":0,"rs3_total":0,"combined_total":0,"osrs_rank":740383,"rs3_rank":805700,"combined_rank":815725,"leagues":{"TBL":[0,37925,null]},"perfect_osrs":false,"perfect_rs3":false,"perfect_combined":false},"48e044ef8b":{"name":"z3rk3run3s","key":"z3rk3run3s","osrs_total":92885,"rs3_total":0,"combined_total":92885,"osrs_rank":21500,"rs3_rank":805720,"combined_rank":24088,"leagues":{"SRL":[32365,8732,"Rune"],"TBLR":[34570,37712,"Adamant"],"REL":[25950,129941,"Mithril"]},"perfect_osrs":false,"perfect_rs3":false,"perfect_combined":false},"aa741d4930":{"name":"Z3R0 CO0L","key":"z3r0 co0l","osrs_total":89115,"rs3_total":0,"combined_total":89115,"osrs_rank":24108,"rs3_rank":805704,"combined_rank":27001,"leagues":{"SRL":[29115,11032,"Adamant"],"REL":[60000,22652,"Dragon"]},"perfect_osrs":false,"perfect_rs3":false,"perfect_combined":false},"538b6bbfcf":{"name":"Z3R0GRVTY","key":"z3r0grvty","osrs_total":20565,"rs3_total":0,"combined_total":20565,"osrs_rank":269740,"rs3_rank":805711,"combined_rank":297047,"leagues":{"SRL":[20565,22610,"Adamant"]},"perfect_osrs":false,"perfect_rs3":false,"perfect_combined":false},"5e5efcd90b":{"name":"Z3U5","key":"z3u5","osrs_total":15880,"rs3_total":0,"combined_total":15880,"osrs_rank":322441,"rs3_rank":805728,"combined_rank":352562,"leagues":{"SRL":[15880,35331,"Adamant"]},"perfect_osrs":false,"perfect_rs3":false,"perfect_combined":false},"5fed89615e":{"name":"Z3C0","key":"z3c0","osrs_total":19405,"rs3_total":0,"combined_total":19405,"osrs_rank":282003,"rs3_rank":805682,"combined_rank":309735,"leagues":{"SRL":[7935,62928,"Mithril"],"TBLR":[11470,176749,"Steel"]},"perfect_osrs":false,"perfect_rs3":false,"perfect_combined":false},"6c16edb56b":{"name":"Z3rm4TT","key":"z3rm4tt","osrs_total":3645,"rs3_total":0,"combined_total":3645,"osrs_rank":502531,"rs3_rank":805722,"combined_rank":550474,"leagues":{"SRL":[3645,86294,"Steel"]},"perfect_osrs":false,"perfect_rs3":false,"perfect_combined":false},"e4d9b2c94e":{"name":"Z3 US","key":"z3 us","osrs_total":3455,"rs3_total":0,"combined_total":3455,"osrs_rank":507616,"rs3_rank":805677,"combined_rank":556087,"leagues":{"SRL":[3455,88225,"Steel"]},"perfect_osrs":false,"perfect_rs3":false,"perfect_combined":false},"294e019242":{"name":"z3rk f0rce","key":"z3rk f0rce","osrs_total":17205,"rs3_total":0,"combined_total":17205,"osrs_rank":306653,"rs3_rank":805718,"combined_rank":335479,"leagues":{"SRL":[2445,96745,"Steel"],"TBLR":[3520,253899,"Bronze"],"REL":[11240,237992,"Steel"]},"perfect_osrs":false,"perfect_rs3":false,"perfect_combined":false},"c8b7cf2233":{"name":"Z3DS","key":"z3ds","osrs_total":6735,"rs3_total":0,"combined_total":6735,"osrs_rank":437401,"rs3_rank":805683,"combined_rank":478668,"leagues":{"SRL":[2095,101174,"Steel"],"REL":[4640,303805,"Iron"]},"perfect_osrs":false,"perfect_rs3":false,"perfect_combined":false},"606e289b77":{"name":"Z3ROK0OL","key":"z3rok0ol","osrs_total":69655,"rs3_total":0,"combined_total":69655,"osrs_rank":42543,"rs3_rank":805724,"combined_rank":47291,"leagues":{"SRL":[485,145237,"Iron"],"TBLR":[35000,36577,"Adamant"],"REL":[34170,62820,"Adamant"]},"perfect_osrs":false,"perfect_rs3":false,"perfect_combined":false},"a978fefe9d":{"name":"Z3von","key":"z3von","osrs_total":2890,"rs3_total":0,"combined_total":2890,"osrs_rank":524881,"rs3_rank":805730,"combined_rank":574846,"leagues":{"SRL":[370,151734,"Bronze"],"TBLR":[2520,270878,"Bronze"]},"perfect_osrs":false,"perfect_rs3":false,"perfect_combined":false},"dd97d0a406":{"name":"Z33THS","key":"z33ths","osrs_total":310,"rs3_total":0,"combined_total":310,"osrs_rank":678306,"rs3_rank":805679,"combined_rank":750409,"leagues":{"SRL":[310,155500,"Bronze"]},"perfect_osrs":false,"perfect_rs3":false,"perfect_combined":false},"b600dde40a":{"name":"Z3R0S3","key":"z3r0s3","osrs_total":310,"rs3_total":0,"combined_total":310,"osrs_rank":678317,"rs3_rank":805715,"combined_rank":750420,"leagues":{"SRL":[310,155519,"Bronze"]},"perfect_osrs":false,"perfect_rs3":false,"perfect_combined":false},"e4c5d91478":{"name":"Z3r0 H3r0","key":"z3r0 h3r0","osrs_total":105,"rs3_total":0,"combined_total":105,"osrs_rank":725493,"rs3_rank":805705,"combined_rank":800836,"leagues":{"SRL":[105,180159,"Bronze"]},"perfect_osrs":false,"perfect_rs3":false,"perfect_combined":false},"d8d54be15d":{"name":"Z3s","key":"z3s","osrs_total":116030,"rs3_total":0,"combined_total":116030,"osrs_rank":11601,"rs3_rank":805725,"combined_rank":13190,"leagues":{"TBLR":[56000,11321,"Dragon"],"REL":[60030,16119,"Dragon"]},"perfect_osrs":false,"perfect_rs3":false,"perfect_combined":false},"f6a614f6d7":{"name":"Z3r0 of Time","key":"z3r0 of time","osrs_total":42300,"rs3_total":0,"combined_total":42300,"osrs_rank":116954,"rs3_rank":805707,"combined_rank":130892,"leagues":{"TBLR":[42300,21911,"Rune"]},"perfect_osrs":false,"perfect_rs3":false,"perfect_combined":false},"c65f407fd0":{"name":"z3rkville","key":"z3rkville","osrs_total":31500,"rs3_total":0,"combined_total":31500,"osrs_rank":167468,"rs3_rank":805721,"combined_rank":185462,"leagues":{"TBLR":[31500,48530,"Adamant"]},"perfect_osrs":false,"perfect_rs3":false,"perfect_combined":false},"5a98c619a9":{"name":"z3 kiwi","key":"z3 kiwi","osrs_total":26690,"rs3_total":0,"combined_total":26690,"osrs_rank":212512,"rs3_rank":805675,"combined_rank":233620,"leagues":{"TBLR":[26690,79836,"Mithril"]},"perfect_osrs":false,"perfect_rs3":false,"perfect_combined":false},"22c1aa551f":{"name":"z3rk deez","key":"z3rk deez","osrs_total":20830,"rs3_total":0,"combined_total":20830,"osrs_rank":267217,"rs3_rank":805717,"combined_rank":294480,"leagues":{"TBLR":[20830,117090,"Mithril"]},"perfect_osrs":false,"perfect_rs3":false,"perfect_combined":false},"7b7f3d7b06":{"name":"Z3R0 XK2","key":"z3r0 xk2","osrs_total":20490,"rs3_total":0,"combined_total":20490,"osrs_rank":270478,"rs3_rank":805708,"combined_rank":297811,"leagues":{"TBLR":[20490,118746,"Mithril"]},"perfect_osrs":false,"perfect_rs3":false,"perfect_combined":false},"a9a93f9847":{"name":"Z 3P0","key":"z 3p0","osrs_total":52990,"rs3_total":0,"combined_total":52990,"osrs_rank":83382,"rs3_rank":805230,"combined_rank":93890,"leagues":{"TBLR":[19960,121603,"Mithril"],"REL":[33030,67823,"Adamant"]},"perfect_osrs":false,"perfect_rs3":false,"perfect_combined":false},"feb3353118":{"name":"Z3taaaaaaaar","key":"z3taaaaaaaar","osrs_total":18190,"rs3_total":0,"combined_total":18190,"osrs_rank":295297,"rs3_rank":805726,"combined_rank":323552,"leagues":{"TBLR":[18190,133347,"Mithril"]},"perfect_osrs":false,"perfect_rs3":false,"perfect_combined":false},"dc3560b501":{"name":"z3nn","key":"z3nn","osrs_total":17980,"rs3_total":8720,"combined_total":26700,"osrs_rank":297821,"rs3_rank":52273,"combined_rank":233491,"leagues":{"TBLR":[17980,135581,"Steel"],"CATA":[8720,52272,"Iron"]},"perfect_osrs":false,"perfect_rs3":false,"perfect_combined":false},"0b92be00d6":{"name":"Z3npool","key":"z3npool","osrs_total":33060,"rs3_total":0,"combined_total":33060,"osrs_rank":157361,"rs3_rank":805697,"combined_rank":174513,"leagues":{"TBLR":[17940,135803,"Steel"],"REL":[15120,212174,"Steel"]},"perfect_osrs":false,"perfect_rs3":false,"perfect_combined":false},"f5b7ead853":{"name":"Z3KEE","key":"z3kee","osrs_total":14020,"rs3_total":0,"combined_total":14020,"osrs_rank":338025,"rs3_rank":805688,"combined_rank":370960,"leagues":{"TBLR":[14020,161500,"Steel"]},"perfect_osrs":false,"perfect_rs3":false,"perfect_combined":false},"ccfefa26d4":{"name":"Z3R0L1M1T5","key":"z3r0l1m1t5","osrs_total":39480,"rs3_total":0,"combined_total":39480,"osrs_rank":126892,"rs3_rank":805713,"combined_rank":141643,"leagues":{"TBLR":[12920,166552,"Steel"],"REL":[26560,121790,"Mithril"]},"perfect_osrs":false,"perfect_rs3":false,"perfect_combined":false},"c4722d9988":{"name":"z3ikki","key":"z3ikki","osrs_total":32000,"rs3_total":1480,"combined_total":33480,"osrs_rank":164105,"rs3_rank":90244,"combined_rank":171886,"leagues":{"TBLR":[10250,186846,"Steel"],"REL":[21750,158596,"Mithril"],"CATA":[1480,90243,null]},"perfect_osrs":false,"perfect_rs3":false,"perfect_combined":false},"b0d87a35b7":{"name":"Z3R0 IM","key":"z3r0 im","osrs_total":25820,"rs3_total":0,"combined_total":25820,"osrs_rank":223563,"rs3_rank":805706,"combined_rank":245239,"leagues":{"TBLR":[8980,197461,"Iron"],"REL":[16840,201380,"Steel"]},"perfect_osrs":false,"perfect_rs3":false,"perfect_combined":false},"a1cea41626":{"name":"z3nmonke","key":"z3nmonke","osrs_total":15470,"rs3_total":0,"combined_total":15470,"osrs_rank":326197,"rs3_rank":805694,"combined_rank":356955,"leagues":{"TBLR":[4730,239198,"Bronze"],"REL":[10740,242825,"Steel"]},"perfect_osrs":false,"perfect_rs3":false,"perfect_combined":false},"99abd10293":{"name":"Z3H3","key":"z3h3","osrs_total":3920,"rs3_total":0,"combined_total":3920,"osrs_rank":496256,"rs3_rank":805686,"combined_rank":543344,"leagues":{"TBLR":[3920,249797,"Bronze"]},"perfect_osrs":false,"perfect_rs3":false,"perfect_combined":false},"faf36ee967":{"name":"Z 33","key":"z 33","osrs_total":9930,"rs3_total":0,"combined_total":9930,"osrs_rank":387796,"rs3_rank":805228,"combined_rank":423435,"leagues":{"TBLR":[3350,256283,"Bronze"],"REL":[6580,285914,"Iron"]},"perfect_osrs":false,"perfect_rs3":false,"perfect_combined":false},"a90a2e0ba3":{"name":"Z3NTIS","key":"z3ntis","osrs_total":3080,"rs3_total":0,"combined_total":3080,"osrs_rank":518988,"rs3_rank":805699,"combined_rank":568271,"leagues":{"TBLR":[2070,280521,null],"REL":[1010,360012,null]},"perfect_osrs":false,"perfect_rs3":false,"perfect_combined":false},"eaa8f80688":{"name":"Z 3 N O","key":"z 3 n o","osrs_total":10960,"rs3_total":0,"combined_total":10960,"osrs_rank":372015,"rs3_rank":805226,"combined_rank":406668,"leagues":{"TBLR":[750,314986,null],"REL":[10210,248346,"Steel"]},"perfect_osrs":false,"perfect_rs3":false,"perfect_combined":false},"1ef43196d9":{"name":"Z3rogames","key":"z3rogames","osrs_total":410,"rs3_total":0,"combined_total":410,"osrs_rank":663048,"rs3_rank":805723,"combined_rank":733485,"leagues":{"TBLR":[410,331471,null]},"perfect_osrs":false,"perfect_rs3":false,"perfect_combined":false},"66cdcf2be7":{"name":"Z 3R0","key":"z 3r0","osrs_total":62130,"rs3_total":0,"combined_total":62130,"osrs_rank":54292,"rs3_rank":805231,"combined_rank":61739,"leagues":{"REL":[62130,4312,"Dragon"]},"perfect_osrs":false,"perfect_rs3":false,"perfect_combined":false},"cfa59f6a0f":{"name":"Z3LE","key":"z3le","osrs_total":45550,"rs3_total":0,"combined_total":45550,"osrs_rank":104552,"rs3_rank":805691,"combined_rank":117066,"leagues":{"REL":[45550,34197,"Rune"]},"perfect_osrs":false,"perfect_rs3":false,"perfect_combined":false},"c17b45378b":{"name":"Z3R0","key":"z3r0","osrs_total":39440,"rs3_total":0,"combined_total":39440,"osrs_rank":127034,"rs3_rank":805702,"combined_rank":141791,"leagues":{"REL":[39440,47905,"Adamant"]},"perfect_osrs":false,"perfect_rs3":false,"perfect_combined":false},"7796c7ef36":{"name":"Z3r0P","key":"z3r0p","osrs_total":36300,"rs3_total":0,"combined_total":36300,"osrs_rank":140040,"rs3_rank":805714,"combined_rank":155776,"leagues":{"REL":[36300,55443,"Adamant"]},"perfect_osrs":false,"perfect_rs3":false,"perfect_combined":false},"a5fcc2f04d":{"name":"z3m0s","key":"z3m0s","osrs_total":24690,"rs3_total":8030,"combined_total":32720,"osrs_rank":237812,"rs3_rank":54495,"combined_rank":176700,"leagues":{"REL":[24690,145767,"Mithril"],"CATA":[8030,54494,"Iron"]},"perfect_osrs":false,"perfect_rs3":false,"perfect_combined":false},"ef1458280c":{"name":"Z3lv","key":"z3lv","osrs_total":21230,"rs3_total":0,"combined_total":21230,"osrs_rank":263486,"rs3_rank":805692,"combined_rank":290618,"leagues":{"REL":[21230,162137,"Mithril"]},"perfect_osrs":false,"perfect_rs3":false,"perfect_combined":false},"6f99dbac23":{"name":"Z3ldin","key":"z3ldin","osrs_total":20470,"rs3_total":0,"combined_total":20470,"osrs_rank":270697,"rs3_rank":805690,"combined_rank":298038,"leagues":{"REL":[20470,168181,"Mithril"]},"perfect_osrs":false,"perfect_rs3":false,"perfect_combined":false},"bd5adbc01c":{"name":"Z3DSD4DDY","key":"z3dsd4ddy","osrs_total":19480,"rs3_total":0,"combined_total":19480,"osrs_rank":281295,"rs3_rank":805685,"combined_rank":308998,"leagues":{"REL":[19480,177547,"Steel"]},"perfect_osrs":false,"perfect_rs3":false,"perfect_combined":false},"8d97549c33":{"name":"Z3DS DE4D","key":"z3ds de4d","osrs_total":16950,"rs3_total":0,"combined_total":16950,"osrs_rank":309766,"rs3_rank":805684,"combined_rank":338800,"leagues":{"REL":[16950,200334,"Steel"]},"perfect_osrs":false,"perfect_rs3":false,"perfect_combined":false},"662f32e7e0":{"name":"Z3M3K","key":"z3m3k","osrs_total":16250,"rs3_total":0,"combined_total":16250,"osrs_rank":318212,"rs3_rank":805693,"combined_rank":347892,"leagues":{"REL":[16250,206721,"Steel"]},"perfect_osrs":false,"perfect_rs3":false,"perfect_combined":false},"d238a12d15":{"name":"Z 3 T S U Z","key":"z 3 t s u z","osrs_total":13180,"rs3_total":0,"combined_total":13180,"osrs_rank":345681,"rs3_rank":805227,"combined_rank":379286,"leagues":{"REL":[13180,223439,"Steel"]},"perfect_osrs":false,"perfect_rs3":false,"perfect_combined":false},"525387dfc3":{"name":"Z3R0H0UR","key":"z3r0h0ur","osrs_total":8480,"rs3_total":0,"combined_total":8480,"osrs_rank":410715,"rs3_rank":805712,"combined_rank":448262,"leagues":{"REL":[8480,268406,"Iron"]},"perfect_osrs":false,"perfect_rs3":false,"perfect_combined":false},"94e3e061f9":{"name":"Z3PHYRION","key":"z3phyrion","osrs_total":8450,"rs3_total":0,"combined_total":8450,"osrs_rank":411185,"rs3_rank":805701,"combined_rank":448790,"leagues":{"REL":[8450,268682,"Iron"]},"perfect_osrs":false,"perfect_rs3":false,"perfect_combined":false},"89171de68c":{"name":"Z3r0Sun","key":"z3r0sun","osrs_total":8090,"rs3_total":0,"combined_total":8090,"osrs_rank":417480,"rs3_rank":805716,"combined_rank":455691,"leagues":{"REL":[8090,272901,"Iron"]},"perfect_osrs":false,"perfect_rs3":false,"perfect_combined":false},"96979b8277":{"name":"Z3ztra","key":"z3ztra","osrs_total":7670,"rs3_total":0,"combined_total":7670,"osrs_rank":424029,"rs3_rank":805733,"combined_rank":463102,"leagues":{"REL":[7670,275878,"Iron"]},"perfect_osrs":false,"perfect_rs3":false,"perfect_combined":false},"287ed2116b":{"name":"z34x","key":"z34x","osrs_total":6080,"rs3_total":0,"combined_total":6080,"osrs_rank":450233,"rs3_rank":805681,"combined_rank":493093,"leagues":{"REL":[6080,291435,"Iron"]},"perfect_osrs":false,"perfect_rs3":false,"perfect_combined":false},"7f0bfff202":{"name":"Z3R0BLEAKZ","key":"z3r0bleakz","osrs_total":5020,"rs3_total":0,"combined_total":5020,"osrs_rank":472818,"rs3_rank":805709,"combined_rank":517000,"leagues":{"REL":[5020,301534,"Iron"]},"perfect_osrs":false,"perfect_rs3":false,"perfect_combined":false},"a0bc4fa55a":{"name":"Z3ldafan","key":"z3ldafan","osrs_total":4370,"rs3_total":0,"combined_total":4370,"osrs_rank":485923,"rs3_rank":805689,"combined_rank":531589,"leagues":{"REL":[4370,306298,"Iron"]},"perfect_osrs":false,"perfect_rs3":false,"perfect_combined":false},"da1929c89c":{"name":"Z3R0F1AWZ","key":"z3r0f1awz","osrs_total":2080,"rs3_total":0,"combined_total":2080,"osrs_rank":554168,"rs3_rank":805710,"combined_rank":608914,"leagues":{"REL":[2080,335757,"Bronze"]},"perfect_osrs":false,"perfect_rs3":false,"perfect_combined":false},"ce7761bc8c":{"name":"Z3nphy","key":"z3nphy","osrs_total":1480,"rs3_total":0,"combined_total":1480,"osrs_rank":581572,"rs3_rank":805696,"combined_rank":640062,"leagues":{"REL":[1480,348153,null]},"perfect_osrs":false,"perfect_rs3":false,"perfect_combined":false},"e5091d5cb3":{"name":"Z3NN1X","key":"z3nn1x","osrs_total":1310,"rs3_total":0,"combined_total":1310,"osrs_rank":590041,"rs3_rank":805695,"combined_rank":649909,"leagues":{"REL":[1310,351716,null]},"perfect_osrs":false,"perfect_rs3":false,"perfect_combined":false},"3f0d698f9b":{"name":"z3j22p","key":"z3j22p","osrs_total":860,"rs3_total":0,"combined_total":860,"osrs_rank":618473,"rs3_rank":805687,"combined_rank":683156,"leagues":{"REL":[860,364347,null]},"perfect_osrs":false,"perfect_rs3":false,"perfect_combined":false},"f0e69fdc38":{"name":"z3rk1ng0ff","key":"z3rk1ng0ff","osrs_total":750,"rs3_total":0,"combined_total":750,"osrs_rank":627170,"rs3_rank":805719,"combined_rank":693416,"leagues":{"REL":[750,367585,null]},"perfect_osrs":false,"perfect_rs3":false,"perfect_combined":false},"ec7e633aee":{"name":"z 33 skiller","key":"z 33 skiller","osrs_total":660,"rs3_total":0,"combined_total":660,"osrs_rank":634624,"rs3_rank":805229,"combined_rank":701662,"leagues":{"REL":[660,369863,null]},"perfect_osrs":false,"perfect_rs3":false,"perfect_combined":false},"858b2bf1b2":{"name":"Z3TWEAVER","key":"z3tweaver","osrs_total":350,"rs3_total":0,"combined_total":350,"osrs_rank":672506,"rs3_rank":805727,"combined_rank":743934,"leagues":{"REL":[350,386262,null]},"perfect_osrs":false,"perfect_rs3":false,"perfect_combined":false},"08a4735241":{"name":"Z3r0 Hope","key":"z3r0 hope","osrs_total":0,"rs3_total":24320,"combined_total":24320,"osrs_rank":814459,"rs3_rank":26000,"combined_rank":263881,"leagues":{"CATA":[24320,25999,"Mithril"]},"perfect_osrs":false,"perfect_rs3":false,"perfect_combined":false},"6ae97309c1":{"name":"z3rek","key":"z3rek","osrs_total":0,"rs3_total":7860,"combined_total":7860,"osrs_rank":814460,"rs3_rank":55123,"combined_rank":459786,"leagues":{"CATA":[7860,55122,"Iron"]},"perfect_osrs":false,"perfect_rs3":false,"perfect_combined":false},"4e186712d5":{"name":"Z3nsh1nx","key":"z3nsh1nx","osrs_total":0,"rs3_total":7050,"combined_total":7050,"osrs_rank":814458,"rs3_rank":58359,"combined_rank":472760,"leagues":{"CATA":[7050,58358,"Iron"]},"perfect_osrs":false,"perfect_rs3":false,"perfect_combined":false},"b4fa3723b0":{"name":"Z3BrACaKeS","key":"z3bracakes","osrs_total":0,"rs3_total":2610,"combined_total":2610,"osrs_rank":814456,"rs3_rank":77703,"combined_rank":585460,"leagues":{"CATA":[2610,77702,"Bronze"]},"perfect_osrs":false,"perfect_rs3":false,"perfect_combined":false},"4e9e51d99a":{"name":"z3brasaurus","key":"z3brasaurus","osrs_total":0,"rs3_total":1940,"combined_total":1940,"osrs_rank":814457,"rs3_rank":85558,"combined_rank":615896,"leagues":{"CATA":[1940,85557,null]},"perfect_osrs":false,"perfect_rs3":false,"perfect_combined":false}}